cdsdashboards/__init__.py
cdsdashboards/__main__.py
cdsdashboards/_data.py
cdsdashboards/alembic.ini
cdsdashboards/app.py
cdsdashboards/dashboard.py
cdsdashboards/dbutil.py
cdsdashboards/orm.py
cdsdashboards/pluggymanager.py
cdsdashboards/util.py
cdsdashboards/version.py
cdsdashboards/builder/__init__.py
cdsdashboards/builder/builders.py
cdsdashboards/builder/dockerbuilder.py
cdsdashboards/builder/kubebuilder.py
cdsdashboards/builder/processbuilder.py
cdsdashboards/cdsalembic/README
cdsdashboards/cdsalembic/env.py
cdsdashboards/cdsalembic/script.py.mako
cdsdashboards/cdsalembic/versions/2478e08b1ba2_base.py
cdsdashboards/cdsalembic/versions/260ac5c1a9e0_add_dashboard_presentation_type.py
cdsdashboards/cdsalembic/versions/f353692d88d5_added_templates.py
cdsdashboards/handlers/__init__.py
cdsdashboards/handlers/base.py
cdsdashboards/hubextension/__init__.py
cdsdashboards/hubextension/api.py
cdsdashboards/hubextension/base.py
cdsdashboards/hubextension/core.py
cdsdashboards/hubextension/events.py
cdsdashboards/hubextension/main.py
cdsdashboards/hubextension/spawners/__init__.py
cdsdashboards/hubextension/spawners/variabledocker.py
cdsdashboards/hubextension/spawners/variablekube.py
cdsdashboards/hubextension/spawners/variablelocalprocess.py
cdsdashboards/hubextension/spawners/variablemixin.py
cdsdashboards/hubextension/spawners/variablesudospawner.py
cdsdashboards/hubextension/spawners/variablesystemd.py
cdsdashboards/hubextension/spawners/variableusercreating.py
cdsdashboards-0.6.3.data/data/share/cdsdashboards/static/favicon.ico
cdsdashboards-0.6.3.data/data/share/cdsdashboards/static/components/jquery.easytabs.js
cdsdashboards-0.6.3.data/data/share/cdsdashboards/static/components/selectator/fm.selectator.jquery.css
cdsdashboards-0.6.3.data/data/share/cdsdashboards/static/components/selectator/fm.selectator.jquery.js
cdsdashboards-0.6.3.data/data/share/cdsdashboards/static/css/style.css
cdsdashboards-0.6.3.data/data/share/cdsdashboards/static/js/alldashboards.js
cdsdashboards-0.6.3.dist-info/LICENSE
cdsdashboards-0.6.3.dist-info/METADATA
cdsdashboards-0.6.3.dist-info/WHEEL
cdsdashboards-0.6.3.dist-info/entry_points.txt
cdsdashboards-0.6.3.dist-info/top_level.txt
cdsdashboards-0.6.3.dist-info/RECORD
