Metadata-Version: 2.1
Name: cdsdashboards
Version: 0.6.3
Summary: ContainDS Dashboards extension for JupyterHub
Home-page: https://github.com/ideonate/cdsdashboards
Author: Ideonate
Author-email: dan@containds.com
License: BSD
Project-URL: Source, https://github.com/ideonate/cdsdashboards
Project-URL: Tracker, https://github.com/ideonate/cdsdashboards/issues
Keywords: containds jupyterhub
Platform: Linux
Platform: Mac OS X
Classifier: Intended Audience :: Developers
Classifier: Intended Audience :: System Administrators
Classifier: Intended Audience :: Science/Research
Classifier: License :: OSI Approved :: BSD License
Classifier: Programming Language :: Python
Classifier: Programming Language :: Python :: 3
Requires-Python: >=3.6
Requires-Dist: tornado (>=6.0.4)
Requires-Dist: traitlets
Requires-Dist: jupyterhub (>=1.0.0)
Requires-Dist: alembic
Requires-Dist: pluggy
Provides-Extra: sudospawner
Requires-Dist: sudospawner (>=0.5.2) ; extra == 'sudospawner'
Provides-Extra: user
Requires-Dist: jhsingle-native-proxy (>=0.7.6) ; extra == 'user'
Requires-Dist: plotlydash-tornado-cmd (>=0.0.6) ; extra == 'user'
Requires-Dist: bokeh-root-cmd (>=0.1.2) ; extra == 'user'
Requires-Dist: rshiny-server-cmd (>=0.0.2) ; extra == 'user'
